dcrypt/__init__.py
dcrypt/base.py
dcrypt/cryptkey.py
dcrypt/exceptions.py
dcrypt/json.py
dcrypt/object.py
dcrypt/signature.py
dcrypt/text.py
dcrypt-0.0.6.dist-info/LICENSE
dcrypt-0.0.6.dist-info/METADATA
dcrypt-0.0.6.dist-info/WHEEL
dcrypt-0.0.6.dist-info/top_level.txt
dcrypt-0.0.6.dist-info/RECORD
