Metadata-Version: 2.1
Name: dcrypt
Version: 0.0.6
Summary: Encrypt text and Python objects using RSA + Fernet encryption.
Author-email: ti-oluwa <tioluwa.dev@gmail.com>
Maintainer-email: ti-oluwa <tioluwa.dev@gmail.com>
Project-URL: Homepage, https://github.com/ti-oluwa/dcrypt
Project-URL: Bug Tracker, https://github.com/ti-oluwa/dcrypt/issues
Project-URL: Repository, https://github.com/ti-oluwa/dcrypt
Keywords: encryption,decryption,rsa,fernet,cryptography
Classifier: Programming Language :: Python :: 3
Classifier: License :: OSI Approved :: MIT License
Classifier: Operating System :: OS Independent
Classifier: Development Status :: 4 - Beta
Classifier: Intended Audience :: Developers
Classifier: Topic :: Software Development :: Libraries :: Python Modules
Classifier: Topic :: Utilities
Classifier: Natural Language :: English
Classifier: Typing :: Typed
Requires-Python: >=3.7
License-File: LICENSE
Requires-Dist: cryptography >=41.0.4
Requires-Dist: rsa >=4.9
Requires-Dist: simple-file-handler >=0.0.1
